axew/__init__.py
axew/client.py
axew/entry.py
axew/exceptions.py
axew-1.0.7.dist-info/METADATA
axew-1.0.7.dist-info/WHEEL
axew-1.0.7.dist-info/top_level.txt
axew-1.0.7.dist-info/RECORD
