Metadata-Version: 2.1
Name: axew
Version: 1.0.7
Summary: Python bindings for Arcane
Home-page: https://github.com/MenuDocs/Axew
Author: Menudocs
Author-email: contact@menudocs.org
License: UNKNOWN
Platform: UNKNOWN
Classifier: Programming Language :: Python :: 3
Classifier: License :: OSI Approved :: MIT License
Classifier: Operating System :: OS Independent
Classifier: Development Status :: 5 - Production/Stable
Requires-Python: >=3.8
Requires-Dist: requests
Requires-Dist: aiohttp
